[{
  "_id": {
    "$oid": "66b9f55fbc5595a4d344f763"
  },
  "id": "1",
  "description": "Chất Thô mềm\n\nFreesize<60 kg\n\n🌸🌸🌸🌸🌸🌸🌸🌸🌸🤡🤡\n\nCác bạn chú ý đọc Thông tin sp trước khi đặt hàng \n\nShop chỉ chuyển đơn theo đúng phân loại khách chọn trong đơn ..\n\n🌺🌺🌺\n\n  Hướng dẫn ĐẶT HÀNG được FREESHIP 😍😍😍\n\n✔ Nếu các bạn mua 1 sản phẩm, vui lòng ấn mua ngay \n\n✔ Nếu các bạn mua từ 2 sản phẩm trở lên, vui lòng ấn thêm vào giỏ hàng, và lần lượt thêm các sản phẩm bạn muốn mua vào giỏ trước khi đặt hàng và thanh toán. Các bạn nên tận dụng mã giảm giá vận chuyển của shopee bằng cách đặt đơn hàng trên 150k nếu bạn ở Hà Nội, trên 250k ở các tỉnh thành còn lại nhé, điều này sẽ giúp mình tiết kiệm được kha khá tiền đó ạ. ",
  "oldPrice": 100000,
  "picUrl": [
    "https://firebasestorage.googleapis.com/v0/b/appmobileshop-b7ca3.appspot.com/o/img_quan_nu_1_1.jfif?alt=media&token=795dd98d-3116-43b3-8738-86d466355912",
    "https://firebasestorage.googleapis.com/v0/b/appmobileshop-b7ca3.appspot.com/o/img_quan_nu_1_2.jfif?alt=media&token=6a11b9df-e48f-451a-9a94-be068a64bc2f",
    "https://firebasestorage.googleapis.com/v0/b/appmobileshop-b7ca3.appspot.com/o/img_quan_nu_1_3.jfif?alt=media&token=f3412da2-68fd-4a67-ab6a-674ee6f68140",
    "https://firebasestorage.googleapis.com/v0/b/appmobileshop-b7ca3.appspot.com/o/img_quan_nu_1_4.jfif?alt=media&token=b2a49ab5-02d0-4003-b387-b13700c72839"
  ],
  "des": "Quần Ống Rộng Nữ Kẻ Nhiều Màu Ulzzang ",
  "price": 89000,
  "rating": 4.3,
  "review": 10,
  "title": "Quần Ống Rộng Nữ "
},
{
  "_id": {
    "$oid": "66b9f55fbc5595a4d344f764"
  },
  "id": "2",
  "description": "- Chất liệu: Quần ống rộng được shop xử dụng chất vải tuyết mưa ( hàng loại 1) nên dày dặn, có độ mềm mại và thấm mồ hôi rất tốt. Đảm bảo không sử dụng phải pha giá rẻ như nhiều bên khác !\n\n- Mẫu quần ống suông là thiết kế kinh điển không thể thiếu trong tủ đồ của mỗi người bởi nó có thể phù hợp cho các bạn dù đang đi học, đi làm hay đi chơi\nVới thiết kế hiện đại, trẻ trung quần ống suông cạp cao nữ trở thành những món đồ không thể thiếu cho các bạn nữ hiện nay vì cực kì dễ mix đồ, với nhiều phong cách khác nhau ",
  "oldPrice": 200000,
  "picUrl": [
    "https://firebasestorage.googleapis.com/v0/b/appmobileshop-b7ca3.appspot.com/o/img_quan_nu_2_1.jfif?alt=media&token=2704b833-7c40-4d76-984c-5f310beaf911",
    "https://firebasestorage.googleapis.com/v0/b/appmobileshop-b7ca3.appspot.com/o/img_quan_nu_2_2.jfif?alt=media&token=2ec0bcf7-a7c2-4d04-949a-9c2a6fdf2a4f",
    "https://firebasestorage.googleapis.com/v0/b/appmobileshop-b7ca3.appspot.com/o/img_quan_nu_2_3.jfif?alt=media&token=e90ab503-8b2c-462e-bd5d-1f37905e862e",
    "https://firebasestorage.googleapis.com/v0/b/appmobileshop-b7ca3.appspot.com/o/img_quan_nu_2_4.jfif?alt=media&token=5d67b6a1-eb86-454e-81d1-0f6c46cfd530"
  ],
  "des": "Quần jean xuông ly trước ống rộng thời trang phong cách QU20 ",
  "price": 169000,
  "rating": 4.1,
  "review": 10,
  "title": "Quần jean xuông ly trước "
},
{
  "_id": {
    "$oid": "66b9f55fbc5595a4d344f765"
  },
  "id": "3",
  "description": "🌸👚 Hàng  nữ của shop là hàng freesize\n\n 🌸🌸\n\n🌸🌸🌸\n\n🌸🌸🌸🌸From nữ : cao m62 nặng 55kg đổ lại là đẹp nhé\n\n⭐️Mẫu chủ đạo với màu như ảnh❤️❤️❤️❤️\n\n🌼\n\n🌸🌸Shop sẽ gửi đơn theo đúng phân loại hàng mà khách đặt trong đơn. \n\n🌹🌹🌹🌹🌹🌹🌼🌼🌼🌼🌼🌼🌹🌹🌹🌹🌹🌹 ",
  "oldPrice": 60000,
  "picUrl": [
    "https://firebasestorage.googleapis.com/v0/b/appmobileshop-b7ca3.appspot.com/o/img_quan_nu_3_1.jfif?alt=media&token=fe181833-a804-4728-8cd2-9f429356ae73",
    "https://firebasestorage.googleapis.com/v0/b/appmobileshop-b7ca3.appspot.com/o/img_quan_nu_3_2.jfif?alt=media&token=c1293c6a-7e25-41f5-b788-f182848d7704",
    "https://firebasestorage.googleapis.com/v0/b/appmobileshop-b7ca3.appspot.com/o/img_quan_nu_3_3.jfif?alt=media&token=647cccc3-0158-427a-b5f4-9b262036924d",
    "https://firebasestorage.googleapis.com/v0/b/appmobileshop-b7ca3.appspot.com/o/img_quan_nu_3_4.jfif?alt=media&token=3769f46d-858e-433c-9cac-dd9bb454e019"
  ],
  "des": "Quần ĐÙI in hình cute / quần đùi in hình dễ thương / quần đùi in hình đáng yêu /",
  "price": 39000,
  "rating": 4.9,
  "review": 10,
  "title": "Quần ĐÙI in hình cute "
},
{
  "_id": {
    "$oid": "66b9f55fbc5595a4d344f766"
  },
  "id": "4",
  "description": "Quần Đùi Legging Nữ Sknit Dáng Ngắn Nữ Nâng Mông Mùa Hè Năng Động - Quần Biker short dáng ngắn mặc siêu đẹp milow feccre\n\nQuần đùi legging nữ - Knit Short Trendy chất thun dày dặn\nChất liệu : cotton cao cấp dày dặn,dẻo,co giãn 4 chiều \nSize: 4 size\nTrùm sỉ 2x\n-Quần legging đùi cạp chun vải cao cấp co giãn tốt dáng.\n-Cam kết giá tốt nhất thị trường, chất lượng đảm bảo. \n-Uy tín được đảm bảo qua hàng vạn đơn hàng trên khắp cả nước\n-Hàng sản xuất tại Việt Nam, trên dây chuyền xuất khẩu cao cấp ",
  "oldPrice": 50000,
  "picUrl": [
    "https://firebasestorage.googleapis.com/v0/b/appmobileshop-b7ca3.appspot.com/o/img_quan_nu_4_1.jfif?alt=media&token=f0d49f09-5852-44ab-afde-c049c9a05fb8",
    "https://firebasestorage.googleapis.com/v0/b/appmobileshop-b7ca3.appspot.com/o/img_quan_nu_4_2.jfif?alt=media&token=7d3d1d04-4f2f-439c-8bb3-686dd735b41f",
    "https://firebasestorage.googleapis.com/v0/b/appmobileshop-b7ca3.appspot.com/o/img_quan_nu_4_3.jfif?alt=media&token=c8331fbb-1852-4b1a-ad1b-a457deb9a066",
    "https://firebasestorage.googleapis.com/v0/b/appmobileshop-b7ca3.appspot.com/o/img_quan_nu_4_4.jfif?alt=media&token=63912652-78d7-480f-9841-c6f808a3faa6"
  ],
  "des": "Quần Đùi Legging Nữ Sknit Dáng Ngắn Nữ Nâng Mông Mùa Hè Năng Động ",
  "price": 39000,
  "rating": 4.1,
  "review": 10,
  "title": "Quần Đùi Legging Nữ"
},
{
  "_id": {
    "$oid": "66b9f55fbc5595a4d344f767"
  },
  "id": "5",
  "description": "Chất lượng cao, thiết kế độc đáo giúp bạn thu hút mọi ánh nhìn\n- Áo thun co dãn vừa và thoải mái, hình in cao cấp, có thể giặt bằng máy tẹt ga mà không lo hỏng áo\n- Nhiều màu sắc cho bạn lựa chọn\n- Thiết kế thoải mái, phù hợp cho nhiều dịp khác nhau\n- Có thể mặc với quần skinny jeans, quần short, quần yoga hoặc quần âu, là một lựa chọn tốt, phù hợp với trang phục thường ngày / du lịch / mặc ở nhà / công sở / bãi biển\n- Luôn cập nhật những mẫu áo mới nhất , chất nhất , bắt kịp xu hướng thời trang ",
  "oldPrice": 100000,
  "picUrl": [
    "https://firebasestorage.googleapis.com/v0/b/appmobileshop-b7ca3.appspot.com/o/img_quan_nu_5_1.jfif?alt=media&token=c2c6bd31-d4ac-4384-8acf-545d310816c5",
    "https://firebasestorage.googleapis.com/v0/b/appmobileshop-b7ca3.appspot.com/o/img_quan_nu_5_2.jfif?alt=media&token=3b31d6ab-0944-4a66-a0ab-1fbe35522300",
    "https://firebasestorage.googleapis.com/v0/b/appmobileshop-b7ca3.appspot.com/o/img_quan_nu_5_3.jfif?alt=media&token=c40a9ea9-ebc3-4fc1-badb-43cec48101c8",
    "https://firebasestorage.googleapis.com/v0/b/appmobileshop-b7ca3.appspot.com/o/img_quan_nu_5_4.jfif?alt=media&token=327458ff-844d-40b9-8bf6-0294c3ebf2b5"
  ],
  "des": "Quần short nữ cạp cao giá rẻ thời trang đi chơi đi học QU9 ",
  "price": 99000,
  "rating": 4.6,
  "review": 10,
  "title": "Quần short nữ cạp cao"
},
{
  "_id": {
    "$oid": "66b9f55fbc5595a4d344f768"
  },
  "id": "6",
  "description": "☀️chất liệu sản phẩm thun\n\n\n\n🌸👚 Hàng  nữ của shop là hàng freesize\n\n 🌸🌸\n\n🌸🌸🌸🌸From nữ : cao m6 nặng 50kg đổ lại là đẹp nhé\n\n⭐️Mẫu chủ đạo với màu như ảnh❤️❤️❤️❤️\n\n🌼\n\n🌸🌸Shop sẽ gửi đơn theo đúng phân loại hàng mà khách đặt trong đơn. \n\n🌹🌹🌹🌹🌹🌹🌼🌼🌼🌼🌼🌼🌹🌹🌹🌹🌹🌹 ",
  "oldPrice": 200000,
  "picUrl": [
    "https://firebasestorage.googleapis.com/v0/b/appmobileshop-b7ca3.appspot.com/o/img_quan_nu_6_1.jfif?alt=media&token=dec71073-5b2d-4d18-bbc8-f92a4a2aad09",
    "https://firebasestorage.googleapis.com/v0/b/appmobileshop-b7ca3.appspot.com/o/img_quan_nu_6_2.jfif?alt=media&token=37464589-1d16-4b82-802b-28b7d243d8b3",
    "https://firebasestorage.googleapis.com/v0/b/appmobileshop-b7ca3.appspot.com/o/img_quan_nu_6_3.jfif?alt=media&token=faa39570-4f47-47b2-8ab1-b1aa353f0525",
    "https://firebasestorage.googleapis.com/v0/b/appmobileshop-b7ca3.appspot.com/o/img_quan_nu_6_4.jfif?alt=media&token=30d4f06c-ee16-49c8-8bc1-38d9ce4f9df9"
  ],
  "des": "Quần DÀI hình dễ thương / quần hoạt hình / quần ngủ Haiphuc ",
  "price": 119000,
  "rating": 4.6,
  "review": 10,
  "title": "Quần DÀI hình dễ thương "
},
{
  "_id": {
    "$oid": "66b9f55fbc5595a4d344f769"
  },
  "id": "7",
  "description": "Quần Jean Lưng Cao Ống Suông Phối Rách Phong Cách Retro\n\nMàu wash xanh rêu wsah dơ vàng\n\n Size S M L\n\n\n              SỬ DỤNG VÀ BẢO QUẢN\n\n- Giặt tay riêng trong 3 lần đầu tiên.\n\n- Không giặt máy trong lần đầu\n\n- Không sử dụng thuốc tẩy\n\n- Khi phơi lộn trái và không phơi trực tiếp dưới ánh nắng mặt trời ",
  "oldPrice": 200000,
  "picUrl": [
    "https://firebasestorage.googleapis.com/v0/b/appmobileshop-b7ca3.appspot.com/o/img_quan_nu_7_1.jfif?alt=media&token=f2a92cb7-5ea4-43d4-978b-9e1be5e72c7e",
    "https://firebasestorage.googleapis.com/v0/b/appmobileshop-b7ca3.appspot.com/o/img_quan_nu_7_2.jfif?alt=media&token=6a0fd86c-26b7-447e-95ad-97601605bad8",
    "https://firebasestorage.googleapis.com/v0/b/appmobileshop-b7ca3.appspot.com/o/img_quan_nu_7_3.jfif?alt=media&token=751906d6-992f-4375-9853-dff040ebbaae",
    "https://firebasestorage.googleapis.com/v0/b/appmobileshop-b7ca3.appspot.com/o/img_quan_nu_7_4.jfif?alt=media&token=82d46476-a95c-4da7-a5e4-812031d85443"
  ],
  "des": "Quần jean nữ ống suông lưng cao phối rách phong cách Retro Hàn Quốc QU12 ",
  "price": 119000,
  "rating": 4.6,
  "review": 10,
  "title": "Quần jean nữ ống suông "
},
{
  "_id": {
    "$oid": "66b9f55fbc5595a4d344f76a"
  },
  "id": "8",
  "description": "THÔNG TIN SẢN PHẨM : Quần Short Jeans Túi Dài- Kiểu dáng: Cạp cao ngang rốn- phong cách ulzzang- lưng cạp cao ngang rốnLƯU Ý: nếu khách iu thắc mắc trong vấn đề chọn size thì hãy ib trực tiếp để shop tư vấn một cách chính xác hơn nhé.* HƯỚNG DẪN SỬ DỤNG VÀ BẢO QUẢN :- Nên giặt sản phẩm trước khi sử dụng. - Nếu giặt máy, nên chọn chế độ giặt nhẹ và sản phẩm có chất vải phù hợp để bảo quản được lâu. - Không nên sử dụng chất giặt tẩy. - Không nên ngâm chung với trang phục bị ra màu. - Lộn mặt trái khi phơi ",
  "oldPrice": 200000,
  "picUrl": [
    "https://firebasestorage.googleapis.com/v0/b/appmobileshop-b7ca3.appspot.com/o/img_quan_nu_8_1.jfif?alt=media&token=13b9c8d7-1e75-4790-8c72-e4ffb9684b20",
    "https://firebasestorage.googleapis.com/v0/b/appmobileshop-b7ca3.appspot.com/o/img_quan_nu_8_2.jfif?alt=media&token=19ab96be-8d9d-441a-af11-a623abc22ab6",
    "https://firebasestorage.googleapis.com/v0/b/appmobileshop-b7ca3.appspot.com/o/img_quan_nu_8_3.jfif?alt=media&token=1a7316bd-71f1-4eeb-b63d-ff7f68bda2a6",
    "https://firebasestorage.googleapis.com/v0/b/appmobileshop-b7ca3.appspot.com/o/img_quan_nu_8_4.jfif?alt=media&token=25423cd0-2a54-423a-9dbd-a62e47aa1378"
  ],
  "des": "Quần Short Jeans Nữ Quần Bò Nữ Lưng Cao Túi Dài Đủ Màu Chất Vãi Dày Dặn Zenko WSH 012 ",
  "price": 119000,
  "rating": 4.6,
  "review": 10,
  "title": "Quần Short Jeans Nữ Quần Bò "
},
{
  "_id": {
    "$oid": "66b9f55fbc5595a4d344f76b"
  },
  "id": "9",
  "description": "quần ống rộng cạp chun ưng cao \n\n quần suông vải gió mệ mỏng nhẹ mát co giãn thoải mái\n\n quần ống rộng 24cm \n\nquần dài 98 đến 100cm\n\ncó túi 2 bên tiện lợi\n\nQuần ống rộng với họa tiết nơ nhỏ xinh xắn là lựa chọn hoàn hảo cho mùa hè này. Chất liệu gió nhăn mềm mại mang lại cảm giác thoải mái và dễ chịu cho người mặc, đồng thời cũng rất dễ giặt sạch bằng máy.\n\nCạp chun lưng cao: Thiết kế với cạp chun có dây rút điều chỉnh eo, phù hợp với nhiều kích thước khác nhau của người mặc.\n\nTúi hai bên: Quần có túi 2 bên tiện lợi để bạn có thể mang theo điện thoại hay ví tiền khi ra đường.\n\nVới phong cách khỏe khoắn, quần ống suông dáng suông này sẽ là trang phục yêu thích của bạn trong nhiều hoàn cảnh khác nhau. Chiều cao vòng eo được thiết kế ở trung tâm tạo ra sự thuận tiện và thoải mái trong khi di chuyển. Chiều dài quần lai chuẩn theo chiều dài thân người giúp tôn lên chiếc áo crop top hay áo ba-lô ",
  "oldPrice": 200000,
  "picUrl": [
    "https://firebasestorage.googleapis.com/v0/b/appmobileshop-b7ca3.appspot.com/o/img_quan_nu_9_1.jfif?alt=media&token=cc294554-6237-4782-a753-6d67a25e73a8",
    "https://firebasestorage.googleapis.com/v0/b/appmobileshop-b7ca3.appspot.com/o/img_quan_nu_9_2.jfif?alt=media&token=ec90a159-5bd6-4fe2-9c5a-00df0072d87e",
    "https://firebasestorage.googleapis.com/v0/b/appmobileshop-b7ca3.appspot.com/o/img_quan_nu_9_3.jfif?alt=media&token=0a683f20-e3a8-4d17-b4f3-7cd266680998",
    "https://firebasestorage.googleapis.com/v0/b/appmobileshop-b7ca3.appspot.com/o/img_quan_nu_9_4.jfif?alt=media&token=745c552a-89b4-4c9e-aa7f-679dbe54965a"
  ],
  "des": "quần ống rộng vải gió nhăn mềm nhẹ mát hoạ tiết in nơ nhỏ xinh xắn cạp chun lưng cao có dây rút ",
  "price": 119000,
  "rating": 4.6,
  "review": 10,
  "title": "quần ống rộng vải gió "
},
{
  "_id": {
    "$oid": "66b9f55fbc5595a4d344f76c"
  },
  "id": "10",
  "description": "Quần jogger nữ bo gấu trơn vải thun dài da cá quần ống rộng nỉ bigsize thể thao tập gym unisex len tăm mềm dây rút milow \nquần jogger\nquần thể thao\nquần ống rộng\nSỐ LƯỢNG CÓ HẠN. NHANH TAY KẺO LỠ !!! \n\nQuần jogger thể thao unisex chất tổ ong dày dặn phong cách Ulzzang \nQuần jogeer chất tổ ong hot hit nhất mọi thời đại đây ạ. Với thiết kế đơn giản. Chiếc quần mặc lên có cảm giác rất năng động và trẻ chung ạ\nCam kết chất len đẹp ",
  "oldPrice": 200000,
  "picUrl": [
    "https://firebasestorage.googleapis.com/v0/b/appmobileshop-b7ca3.appspot.com/o/img_quan_nu_10_1.jfif?alt=media&token=bd1980ad-8715-4a3d-b128-502375a1c1ee",
    "https://firebasestorage.googleapis.com/v0/b/appmobileshop-b7ca3.appspot.com/o/img_quan_nu_10_2.jfif?alt=media&token=3b16fa33-e82b-49e9-abda-a38ce8cc9e02",
    "https://firebasestorage.googleapis.com/v0/b/appmobileshop-b7ca3.appspot.com/o/img_quan_nu_10_3.jfif?alt=media&token=45d5908a-865b-4c18-bccb-21f0464ba1d0",
    "https://firebasestorage.googleapis.com/v0/b/appmobileshop-b7ca3.appspot.com/o/img_quan_nu_10_4.jfif?alt=media&token=bfb9e645-4c85-4e17-91cd-e250d15e8f97"
  ],
  "des": "Quần jogger nữ bo gấu trơn vải thun dài da cá quần ống rộng nỉ joggers",
  "price": 119000,
  "rating": 4.6,
  "review": 10,
  "title": "Quần jogger nữ bo "
},
{
  "_id": {
    "$oid": "66b9f55fbc5595a4d344f76d"
  },
  "id": "11",
  "description": "Học sinh rơi vào quần tây thẳng và chất vải mềm mại, thoải mái. ",
  "oldPrice": 190000,
  "picUrl": [
    "https://firebasestorage.googleapis.com/v0/b/appmobileshop-b7ca3.appspot.com/o/img_quan_nam_1_1.jfif?alt=media&token=3ee1a736-6b69-42e0-a3da-daea9561b544",
    "https://firebasestorage.googleapis.com/v0/b/appmobileshop-b7ca3.appspot.com/o/img_quan_nam_1_2.jfif?alt=media&token=d48b75d6-0f54-4848-af0f-463f42460452",
    "https://firebasestorage.googleapis.com/v0/b/appmobileshop-b7ca3.appspot.com/o/img_quan_nam_1_3.jfif?alt=media&token=94a9f475-5480-4ba7-9ccf-f2309fa3b60b",
    "https://firebasestorage.googleapis.com/v0/b/appmobileshop-b7ca3.appspot.com/o/img_quan_nam_1_4.jfif?alt=media&token=1781c261-d309-4812-9161-e00d8cec5ed1"
  ],
  "des": "all Fit\nKhông\nChất liệu\nKhác, Sợi dệt\nXuất xứ\nTrung Quốc\nMẫu\nTrơn\nRất lớn\nCó ",
  "price": 121000,
  "rating": 4.9,
  "review": 10,
  "title": "Quần crop mỏng nam"
},
{
  "_id": {
    "$oid": "66b9f55fbc5595a4d344f76e"
  },
  "id": "12",
  "description": "Khuyến nghị kích thước\n\nSize M: Vòng eo: 54 ~ 94cm; Vòng hông: 94cm;\n\nSize L: Vòng eo: 58 ~ 98cm; Vòng hông: 98cm;\n\nSize XL: Vòng eo: 62 ~ 102cm; Vòng hông: 102cm;\n\nSize 2XL: Vòng eo: 66 ~ 106cm; Vòng hông: 106cm;\n\nSize 3XL: Vòng eo: 70 ~ 110cm; Vòng hông: 110cm;\n\nSize 4XL: Vòng eo: 74 ~ 114cm; Vòng hông: 114cm;\n\nSize 5XL: Vòng eo: 78 ~ 118cm; Vòng hông: 118cm; ",
  "oldPrice": 180000,
  "picUrl": [
    "https://firebasestorage.googleapis.com/v0/b/appmobileshop-b7ca3.appspot.com/o/img_quan_nam_2_1.jfif?alt=media&token=bf3f4eec-f573-42b3-b1ea-8106c6b0ad34",
    "https://firebasestorage.googleapis.com/v0/b/appmobileshop-b7ca3.appspot.com/o/img_quan_nam_2_2.jfif?alt=media&token=4deae817-942a-4a41-80a1-bb671c4ee831",
    "https://firebasestorage.googleapis.com/v0/b/appmobileshop-b7ca3.appspot.com/o/img_quan_nam_2_3.jfif?alt=media&token=220a5508-73ec-4096-ba7c-edbd12620938",
    "https://firebasestorage.googleapis.com/v0/b/appmobileshop-b7ca3.appspot.com/o/img_quan_nam_2_4.jfif?alt=media&token=13f8655c-3bc7-4a33-a747-8d15a309f617"
  ],
  "des": "Thoải Mái Quá Khổ Năm Điểm Quần Nam Nữ Có Thể Mặc Xanh ",
  "price": 135000,
  "rating": 4.1,
  "review": 10,
  "title": "Quần Short Rời "
},
{
  "_id": {
    "$oid": "66b9f55fbc5595a4d344f76f"
  },
  "id": "13",
  "description": "Sản phẩm: Quần Jogger Nam \n\nChất liệu: Vải mềm mại, thoáng mát dễ thấm hút mồ hôi\n\nKiểu dáng đơn giản nhưng không kém phần thời trang, phong cách\n\nPhù hợp khi đi chơi, dạo phố cùng bạn bè…\n\nSize S: cho người từ 50kg trở xuống tùy chiều cao\n\nSize M: cho người từ 55kg trở xuống tùy chiều cao\n\nSize L: cho người từ 60kg trở xuống tùy chiều cao\n\nSize XL: Dành cho người từ 65kg trở xuống tùy chiều cao ",
  "oldPrice": 80000,
  "picUrl": [
    "https://firebasestorage.googleapis.com/v0/b/appmobileshop-b7ca3.appspot.com/o/img_quan_nam_3_1.jfif?alt=media&token=4fc48a8a-fd17-46aa-bea7-d640873ff4c2",
    "https://firebasestorage.googleapis.com/v0/b/appmobileshop-b7ca3.appspot.com/o/img_quan_nam_3_2.jfif?alt=media&token=7ed69260-002f-4f66-a72f-9a1dad4d26cd",
    "https://firebasestorage.googleapis.com/v0/b/appmobileshop-b7ca3.appspot.com/o/img_quan_nam_3_3.jfif?alt=media&token=92053831-f553-4f31-bfc1-d61ed53b9e3e",
    "https://firebasestorage.googleapis.com/v0/b/appmobileshop-b7ca3.appspot.com/o/img_quan_nam_3_4.jfif?alt=media&token=36042b5e-91f3-4ecc-aea6-bdff773f83bd"
  ],
  "des": "Kiểu Dáng Thời Trang Tinh Tế Bo Chun Ống Chân Zenkocs3 MEN QUAN 068 ",
  "price": 69000,
  "rating": 4.6,
  "review": 10,
  "title": "Quần Jogger Nam "
},
{
  "_id": {
    "$oid": "66b9f55fbc5595a4d344f770"
  },
  "id": "14",
  "description": "Màu sắc: Đen Trắng 90% Chọn hai gói [Tóc thứ hai tại chỗ] Xám Đen A Xám A Kaki A Xanh A Đen + Xám Đen + Trắng Đen + Đen A Đen + Xám A Đen + Kaki A Đen + Xanh A Đen + 210G Áo thun Cotton trắng đen + 210G Cotton Matcha xanh Áo thun đen + 210G Cotton đen tuyền Áo thun đen + 210G Cotton hồng tinh khiết Áo thun đen + 210G Cotton tinh khiết Gạo mơ Áo thun vui lòng nhìn về phía nó, xin vui lòng nhìn Chuyển tiếp đến nó, xin vui lòng chuyển tiếp đến nó 1, xin vui lòng chuyển tiếp đến nó 2, xin vui lòng chuyển tiếp đến nó 3 ",
  "oldPrice": 90000,
  "picUrl": [
    "https://firebasestorage.googleapis.com/v0/b/appmobileshop-b7ca3.appspot.com/o/img_quan_nam_4_1.jfif?alt=media&token=e4b0cadc-199b-4714-8a60-dbd9a02e5342",
    "https://firebasestorage.googleapis.com/v0/b/appmobileshop-b7ca3.appspot.com/o/img_quan_nam_4_2.jfif?alt=media&token=c313fe06-80d2-4959-ac31-0df40eebb7f4",
    "https://firebasestorage.googleapis.com/v0/b/appmobileshop-b7ca3.appspot.com/o/img_quan_nam_4_3.jfif?alt=media&token=b0da930f-9951-45c1-a1ac-151b18922d83",
    "https://firebasestorage.googleapis.com/v0/b/appmobileshop-b7ca3.appspot.com/o/img_quan_nam_4_4.jfif?alt=media&token=be507296-f033-4c96-b800-b28ef8bb120f"
  ],
  "des": "Phong Cách Mùa Hè Năng Động ",
  "price": 59000,
  "rating": 4.5,
  "review": 10,
  "title": "Quần Short Thể Thao "
},
{
  "_id": {
    "$oid": "66b9f55fbc5595a4d344f771"
  },
  "id": "15",
  "description": "Sản Phẩm: Quần ống rộng thể thao nam\n\n- Chất liệu: Vải thun trơn dày dặn, co giãn tốt thất hút mồ hôi, mặc thoáng mát\n\n- Thiết kế : Quần ống rộng thể thao nam basic đơn giản dễ mặc….\n\n- Kiểu dáng gọn nhẹ, thể thao, năng động và đầy cá tính.\n\nPhù hợp nhiều hoàn cảnh: mặc nhà, đi học, đi chơi, du lịch...\n\n- Xuất xứ: Việt Na ",
  "oldPrice": 200000,
  "picUrl": [
    "https://firebasestorage.googleapis.com/v0/b/appmobileshop-b7ca3.appspot.com/o/img_quan_nam_5_1.jfif?alt=media&token=6925bd6b-5c06-4236-90a0-aa0cee2d5090",
    "https://firebasestorage.googleapis.com/v0/b/appmobileshop-b7ca3.appspot.com/o/img_quan_nam_5_2.jfif?alt=media&token=700cb693-4cfd-450d-80c6-cfe8a09a1477",
    "https://firebasestorage.googleapis.com/v0/b/appmobileshop-b7ca3.appspot.com/o/img_quan_nam_5_3.jfif?alt=media&token=883b6575-0b87-4178-9879-2bc9654690f6",
    "https://firebasestorage.googleapis.com/v0/b/appmobileshop-b7ca3.appspot.com/o/img_quan_nam_5_4.jfif?alt=media&token=db023898-e31b-461d-bbe9-3e29568d2b9a"
  ],
  "des": "Mặc 2 Kiểu Có Thể Rút Dây Thành Jogger Bo Gấu Lưng Thun Co Giãn JOGGER NAM 9000064C4 ",
  "price": 119000,
  "rating": 4.7,
  "review": 10,
  "title": "Quần Culottes Ống Rộng "
},
{
  "_id": {
    "$oid": "66b9f55fbc5595a4d344f772"
  },
  "id": "16",
  "description": "😘 Quần Kaki Ống Suôn May Chuẩn Hàng Xuất, Quần Kaki Baggy Nam Nữ chất Kaki mềm HK1970  Ống Đứng Mềm Q179 ",
  "oldPrice": 200000,
  "picUrl": [
    "https://firebasestorage.googleapis.com/v0/b/appmobileshop-b7ca3.appspot.com/o/img_quan_nam_6_1.jfif?alt=media&token=152677a6-e2c0-4ffe-b877-4b297ace22ae",
    "https://firebasestorage.googleapis.com/v0/b/appmobileshop-b7ca3.appspot.com/o/img_quan_nam_6_2.jfif?alt=media&token=4e7a6167-eaab-4ae8-a896-596760917449",
    "https://firebasestorage.googleapis.com/v0/b/appmobileshop-b7ca3.appspot.com/o/img_quan_nam_6_3.jfif?alt=media&token=7458202e-22c4-4bc9-a458-35ba4a1b7953",
    "https://firebasestorage.googleapis.com/v0/b/appmobileshop-b7ca3.appspot.com/o/img_quan_nam_6_4.jfif?alt=media&token=d889d7be-b112-4f7b-b502-3418bb5f956f"
  ],
  "des": "May Chuẩn Hàng Xuất, Quần Kaki Baggy Nam Nữ chất Kaki mềm, Ống Đứng Mềm Q179 ",
  "price": 159000,
  "rating": 4.6,
  "review": 10,
  "title": " Quần Kaki Ống Suông"
},
{
  "_id": {
    "$oid": "66b9f55fbc5595a4d344f773"
  },
  "id": "17",
  "description": "Quần Short Unisex Essentials Phong Cách Thể Thao Chất Cotton Mặc Thoáng Mátư\n✔️ Xuất xứ: Việt Nam\n✔️ Chất liệu: Vải Cotton",
  "oldPrice": 100000,
  "picUrl": [
    "https://firebasestorage.googleapis.com/v0/b/appmobileshop-b7ca3.appspot.com/o/img_quan_nam_7_1.jfif?alt=media&token=f1c87e3c-817d-47d6-a9bf-31b1113c13a7",
    "https://firebasestorage.googleapis.com/v0/b/appmobileshop-b7ca3.appspot.com/o/img_quan_nam_7_2.jfif?alt=media&token=077239e8-0677-4b8d-b2bf-0382527caeb9",
    "https://firebasestorage.googleapis.com/v0/b/appmobileshop-b7ca3.appspot.com/o/img_quan_nam_7_3.jfif?alt=media&token=db3bd1b5-8307-4cf9-8fdf-c7b9c9446a98",
    "https://firebasestorage.googleapis.com/v0/b/appmobileshop-b7ca3.appspot.com/o/img_quan_nam_7_4.jfif?alt=media&token=b3bd6383-3560-4a65-94d7-a254161ee94c"
  ],
  "des": "Phong Cách Thể Thao Chất Cotton Mặc Thoáng Mát ",
  "price": 79000,
  "rating": 4.5,
  "review": 10,
  "title": "Quần Short Unisex Basic "
},
{
  "_id": {
    "$oid": "66b9f55fbc5595a4d344f774"
  },
  "id": "18",
  "description": "Thương hiệu：INCERUN\n\nKích thước: S, M, L, XL, 2XL, 3XL, 4XL,5XL\n\nChất Liệu vải: 100%Polyester\n\nMàu sắc: Đen, Trắng, Xám\n\nPhong cách:Cơ Bản\n\nDịp sử dụng: Giải trí\n\nHoa văn: Màu trơn\n\nĐộ dày: Vừa phải\n\nMô tả sản phẩm : Quần dài nam màu trơn.\n\nNhãn mác: CÓ ",
  "oldPrice": 200000,
  "picUrl": [
    "https://firebasestorage.googleapis.com/v0/b/appmobileshop-b7ca3.appspot.com/o/img_quan_nam_8_1.jfif?alt=media&token=0b3c3667-f7d0-45cf-8cdc-ce8d5c01f7ce",
    "https://firebasestorage.googleapis.com/v0/b/appmobileshop-b7ca3.appspot.com/o/img_quan_nam_8_2.jfif?alt=media&token=916a4ac3-838c-425d-ab01-38bef38f27ca",
    "https://firebasestorage.googleapis.com/v0/b/appmobileshop-b7ca3.appspot.com/o/img_quan_nam_8_3.jfif?alt=media&token=aceb12c4-0b11-413a-ba3d-83d433864c9a",
    "https://firebasestorage.googleapis.com/v0/b/appmobileshop-b7ca3.appspot.com/o/img_quan_nam_8_4.jfif?alt=media&token=4d13f076-530a-4e6f-ad77-6f83bae6fa72"
  ],
  "des": "thẳng rộng rãi dành cho nam có túi bên ",
  "price": 188000,
  "rating": 4.1,
  "review": 10,
  "title": "Incerun Quần xếp ly"
},
{
  "_id": {
    "$oid": "66b9f55fbc5595a4d344f775"
  },
  "id": "19",
  "description": "Mô tả sản phẩm : Quần jean nam ống suông vải đẹp form chuẩn không phai màu cao cấp\n\nHƯNG PHƯỚC FASHION giới thiệu đến các bạn style thời trang năng động trong hè này với Quần Jean Nam dài ống suông vải dày dặn không co giãn form chuẩn với thiết kế đơn giản. Điểm nổi bật của item này là dạng trơn chỉ với 03 màu, không quá cầu kỳ và đơn giản ở mọi góc nhìn tuy nhiên không kém phần sang trọng. Những đường chỉ phá cách, tinh tế dưới túi quần chính là nét tạo nên vẻ đẹp nam tính của anh chàng mạnh mẽ.\nForm quần thiết kế mới nhất theo xu thế thời trang hiện đại. ",
  "oldPrice": 200000,
  "picUrl": [
    "https://firebasestorage.googleapis.com/v0/b/appmobileshop-b7ca3.appspot.com/o/img_quan_nam_9_1.jfif?alt=media&token=e03bc799-da78-4efe-bf31-fe1c0556a254",
    "https://firebasestorage.googleapis.com/v0/b/appmobileshop-b7ca3.appspot.com/o/img_quan_nam_9_2.jfif?alt=media&token=b7f13f5a-0a66-4ee4-876d-351e456583fd",
    "https://firebasestorage.googleapis.com/v0/b/appmobileshop-b7ca3.appspot.com/o/img_quan_nam_9_3.jfif?alt=media&token=b7e94ff7-1dc3-4531-87c7-c94ad97706a2",
    "https://firebasestorage.googleapis.com/v0/b/appmobileshop-b7ca3.appspot.com/o/img_quan_nam_9_4.jfif?alt=media&token=6611ad40-22e6-43d6-9a37-a70f4429eb1e"
  ],
  "des": "Ống Suông Cotton Mền Mịn Vải Dày Dặn Form Chuẩn Không Phai Màu ",
  "price": 119000,
  "rating": 4.6,
  "review": 10,
  "title": "Quần Jean Nam Quần Bò Nam "
},
{
  "_id": {
    "$oid": "66b9f55fbc5595a4d344f776"
  },
  "id": "20",
  "description": "Phong cách: Hàn Quốc\n\nLoại quần: thẳng\n\nChiều dài quần: quần chín điểm\n\nLoại eo: giữa eo\n\nCho dù có thắt lưng: Với thắt lưng\n\nQuần Placket: đóng dây buộc\n\nĐộ dày: Phần mỏng\n\nMô hình: trơn\n\nCho mùa: Mùa hè\n\nPhù hợp với đám đông: thanh thiếu niên ",
  "oldPrice": 200000,
  "picUrl": [
    "https://firebasestorage.googleapis.com/v0/b/appmobileshop-b7ca3.appspot.com/o/img_quan_nam_10_1.jfif?alt=media&token=c4008c45-0a44-4f89-b1de-df77db82c165",
    "https://firebasestorage.googleapis.com/v0/b/appmobileshop-b7ca3.appspot.com/o/img_quan_nam_10_2.jfif?alt=media&token=5bb905b2-60e2-4e35-85cd-0eb81a947680",
    "https://firebasestorage.googleapis.com/v0/b/appmobileshop-b7ca3.appspot.com/o/img_quan_nam_10_3.jfif?alt=media&token=23600ad8-2e73-437d-8962-bca5ecbf2b19",
    "https://firebasestorage.googleapis.com/v0/b/appmobileshop-b7ca3.appspot.com/o/img_quan_nam_10_4.jfif?alt=media&token=80238e56-a781-4cca-a3bf-67fe12eff073"
  ],
  "des": "okang dành cho nam giới Retro của Nhật Bản Quần ống rộng mềm mại thoáng khí nhiều túi ",
  "price": 139000,
  "rating": 4.8,
  "review": 10,
  "title": "Quần ống rộng Aokang "
}]